docs/source/conf.py
ionerdss/__init__.py
ionerdss/gillespie_simulation/__init__.py
ionerdss/gillespie_simulation/simple_gillespie.py
ionerdss/nerdss_analysis/__init__.py
ionerdss/nerdss_analysis/analysis.py
ionerdss/nerdss_analysis/data_readers.py
ionerdss/nerdss_analysis/plot_figures.py
ionerdss/nerdss_analysis/plotting/__init__.py
ionerdss/nerdss_analysis/plotting/heatmap_plots.py
ionerdss/nerdss_analysis/plotting/histogram_plots.py
ionerdss/nerdss_analysis/plotting/line_plots.py
ionerdss/nerdss_analysis/plotting/probability_plots.py
ionerdss/nerdss_analysis/plotting/three_d_plots.py
ionerdss/nerdss_guis/__init__.py
ionerdss/nerdss_guis/gui.py
ionerdss/nerdss_guis/nerdss.py
ionerdss/nerdss_guis/gen/__init__.py
ionerdss/nerdss_guis/gen/advanced_options_parse_pdb.py
ionerdss/nerdss_guis/gen/mainwindow.py
ionerdss/nerdss_guis/gen/modify_parameters.py
ionerdss/nerdss_guis/gen/mplwidget.py
ionerdss/nerdss_guis/gen/nerdss_install.py
ionerdss/nerdss_guis/gen/pdb_movie_player.py
ionerdss/nerdss_guis/gen/plot_complex.py
ionerdss/nerdss_guis/gen/plot_copy_num.py
ionerdss/nerdss_model/PlatonicSolids.py
ionerdss/nerdss_model/__init__.py
ionerdss/nerdss_model/complex.py
ionerdss/nerdss_model/coords.py
ionerdss/nerdss_model/design_model.py
ionerdss/nerdss_model/model.py
ionerdss/nerdss_model/pdb_model.py
ionerdss/nerdss_model/platonic_solids_model.py
ionerdss/nerdss_model/mini_virus/PDB.py
ionerdss/nerdss_model/mini_virus/__init__.py
ionerdss/nerdss_model/mini_virus/angles.py
ionerdss/nerdss_model/mini_virus/chain_int.py
ionerdss/nerdss_model/mini_virus/gagReshape.py
ionerdss/nerdss_model/mini_virus/output_test.py
ionerdss/nerdss_model/platonic_solids/__init__.py
ionerdss/nerdss_model/platonic_solids/cube/__init__.py
ionerdss/nerdss_model/platonic_solids/cube/cube_face.py
ionerdss/nerdss_model/platonic_solids/cube/cube_face_COM_coord.py
ionerdss/nerdss_model/platonic_solids/cube/cube_face_COM_leg_coord.py
ionerdss/nerdss_model/platonic_solids/cube/cube_face_COM_leg_list_gen.py
ionerdss-1.2.2.dist-info/licenses/LICENSE
ionerdss-1.2.2.dist-info/METADATA
ionerdss-1.2.2.dist-info/WHEEL
ionerdss-1.2.2.dist-info/top_level.txt
ionerdss-1.2.2.dist-info/RECORD
