Metadata-Version: 2.4
Name: ioNERDSS
Version: 1.2.2
Summary: Package for preparing NERDSS inputs and analysing outputs.
Author-email: "Zixiu (Hugh) Liu" <zliu140@jhu.edu>, Sikao Guo <sikaoguo@gmail.com>, Mankun Sang <msang2@jhu.edu>
License: GPL-3.0
Keywords: NERDSS Simulation,Model Setup,Analysis Tools
Classifier: Development Status :: 5 - Production/Stable
Classifier: Intended Audience :: Science/Research
Classifier: Operating System :: OS Independent
Classifier: License :: OSI Approved :: GNU General Public License v3 (GPLv3)
Classifier: Programming Language :: Python :: 3
Requires-Python: >=3.8
License-File: LICENSE
Requires-Dist: numpy
Requires-Dist: pandas
Requires-Dist: matplotlib
Requires-Dist: seaborn
Requires-Dist: tqdm
Requires-Dist: PyQt6
Requires-Dist: pyqtgraph
Requires-Dist: PyOpenGL
Requires-Dist: biopython
Requires-Dist: scipy
Requires-Dist: scikit-learn
Requires-Dist: requests
Requires-Dist: nglview
Requires-Dist: ipympl
Requires-Dist: imageio
Requires-Dist: ovito
Requires-Dist: jupyter
Requires-Dist: jupyterlab
Requires-Dist: notebook
Dynamic: license-file
